[
    {
        "sample_idx": 0,
        "input_lang": "nl",
        "output": "1.Introduction:\nIn this essay, I am going to describe what would be like if gravity"
    },
    {
        "sample_idx": 1,
        "input_lang": "nl",
        "output": "19 year old female named Irisa. Was raised by her father who was a powerful sor"
    },
    {
        "sample_idx": 2,
        "input_lang": "nl",
        "output": "1999, the year that saw the release of the highly acclaimed science fiction film,"
    },
    {
        "sample_idx": 3,
        "input_lang": "nl",
        "output": "19 year old female named Iris. she is a thief and pickpocket. she"
    },
    {
        "sample_idx": 4,
        "input_lang": "nl",
        "output": "1 week geleden\nHi there!\nThank you so much for meeting up with me last week"
    },
    {
        "sample_idx": 5,
        "input_lang": "nl",
        "output": "1.000 characters minimum, including subject and signature.\nSubject: Meeting with John to"
    },
    {
        "sample_idx": 6,
        "input_lang": "nl",
        "output": "1. Hi Supervisor,\n2. I hope you are doing well. I recently submitted a"
    },
    {
        "sample_idx": 7,
        "input_lang": "nl",
        "output": "....\n\n---\n\nHi manager,\n\nSorry for missing the project deadline. Here'"
    },
    {
        "sample_idx": 8,
        "input_lang": "nl",
        "output": "100% correcte answer.\n\nHi there,\n\nI am writing to inform"
    },
    {
        "sample_idx": 9,
        "input_lang": "nl",
        "output": "1.000 word essay on the topic of “What is the difference between leadership and management"
    },
    {
        "sample_idx": 10,
        "input_lang": "nl",
        "output": "......\n\nVraag: U hebt een onjuiste afschrijving op"
    },
    {
        "sample_idx": 11,
        "input_lang": "nl",
        "output": "1.000 characters minimum including subject and signature.\n\nSubject: Thank you for your"
    },
    {
        "sample_idx": 12,
        "input_lang": "nl",
        "output": "2019-03-20 10:00\nDear Sir"
    },
    {
        "sample_idx": 13,
        "input_lang": "nl",
        "output": "100% kostenfree en zonder obligationes. voorbeeld:\nDear"
    },
    {
        "sample_idx": 14,
        "input_lang": "nl",
        "output": "2014-03-24 11:45\nDear friend"
    },
    {
        "sample_idx": 15,
        "input_lang": "nl",
        "output": "10 oktober 2018\nDear friend,\nThank you very much for your"
    },
    {
        "sample_idx": 16,
        "input_lang": "nl",
        "output": "1 oktober 2014\nHi guys!\nI know it’s been a while"
    },
    {
        "sample_idx": 17,
        "input_lang": "nl",
        "output": "10-04-2019\nDear friend,\nI am writing this"
    },
    {
        "sample_idx": 18,
        "input_lang": "nl",
        "output": "2014 was a year filled with excitement and adventure. From graduating college and landing my"
    },
    {
        "sample_idx": 19,
        "input_lang": "nl",
        "output": "......\n\n# Email to university admissions office requesting information about a specific program\n\n"
    },
    {
        "sample_idx": 20,
        "input_lang": "nl",
        "output": "100% correcte grammaticale structuren en correcte spelling.\n\n"
    },
    {
        "sample_idx": 21,
        "input_lang": "nl",
        "output": "1 oktober 2018\nlijnbaansplattegrond.pdf (1"
    },
    {
        "sample_idx": 22,
        "input_lang": "nl",
        "output": "1.019 characters including line breaks\nDear Colleagues,\n\nI am"
    },
    {
        "sample_idx": 23,
        "input_lang": "nl",
        "output": ".......\n\nDear former employer,\n\nI am writing to ask if you would be"
    },
    {
        "sample_idx": 24,
        "input_lang": "nl",
        "output": "1. Hi there!\n2. I am writing to introduce you to our company, ABC Consult"
    },
    {
        "sample_idx": 25,
        "input_lang": "nl",
        "output": "1. Hi there,\n2. We are thrilled to announce the release of our latest product"
    },
    {
        "sample_idx": 26,
        "input_lang": "nl",
        "output": "1. Hi there! Thank you for reaching out to us regarding our product. We appreciate your interest"
    },
    {
        "sample_idx": 27,
        "input_lang": "nl",
        "output": "1. Hi John,\nThank you for subscribing to our newsletter. We are thr"
    },
    {
        "sample_idx": 28,
        "input_lang": "nl",
        "output": "1. Hi John,\n2. We hope you are having a great day. We wanted to"
    },
    {
        "sample_idx": 29,
        "input_lang": "nl",
        "output": "1 oktober 2015\nDear sir/madam,\nI am writing this"
    },
    {
        "sample_idx": 30,
        "input_lang": "nl",
        "output": "100% correcte answer!\n\nThis was the answer that Google Translate gave me"
    },
    {
        "sample_idx": 31,
        "input_lang": "nl",
        "output": "1.000 characters minimum, including subject and signature.\n\nSubject: possible collaboration on"
    },
    {
        "sample_idx": 32,
        "input_lang": "nl",
        "output": "1 oktober 2018\nDear sir/madam,\nI am sorry to"
    },
    {
        "sample_idx": 33,
        "input_lang": "nl",
        "output": "1. Describe your situation ( what is your situation now, what is your goal, what is your"
    },
    {
        "sample_idx": 34,
        "input_lang": "nl",
        "output": "1.Some people believe that online learning is more effective than traditional learning, while others claim that classical"
    },
    {
        "sample_idx": 35,
        "input_lang": "nl",
        "output": "1.Some people think that global environmental problems should be solved worldwide, while others think that they should"
    },
    {
        "sample_idx": 36,
        "input_lang": "nl",
        "output": "100% agree. It is much harder to achieve a work-life balance nowadays than"
    },
    {
        "sample_idx": 37,
        "input_lang": "nl",
        "output": "1. sed sed sed sed sed sed sed sed sed sed sed sed sed sed sed sed sed sed"
    },
    {
        "sample_idx": 38,
        "input_lang": "nl",
        "output": "1.Some people think that animal testing is necessary for medical research, while others think it should be"
    },
    {
        "sample_idx": 39,
        "input_lang": "nl",
        "output": "1. young people are not interested in working in agriculture sector because of low remuneration and"
    },
    {
        "sample_idx": 40,
        "input_lang": "nl",
        "output": "Obesity is a growing problem in many countries around the world. It is caused by a combination"
    },
    {
        "sample_idx": 41,
        "input_lang": "nl",
        "output": "1.What are the causes and measures of the problems of water and air pollution in big cities?"
    },
    {
        "sample_idx": 42,
        "input_lang": "nl",
        "output": "1. There is a huge difference between having access to technology and having competence in technology. Having"
    },
    {
        "sample_idx": 43,
        "input_lang": "nl",
        "output": "1. There are many reasons why urban areas are seeing an increase in homelessness. One reason is"
    },
    {
        "sample_idx": 44,
        "input_lang": "nl",
        "output": "1. Climate change is a significant issue for our planet. What do you think are the main"
    },
    {
        "sample_idx": 45,
        "input_lang": "nl",
        "output": "1. Online shopping is becoming increasingly popular due to several reasons such as convenience, time savings, cost"
    },
    {
        "sample_idx": 46,
        "input_lang": "nl",
        "output": "1. In many parts of the world, the number of people who read books has significantly decreased"
    },
    {
        "sample_idx": 47,
        "input_lang": "nl",
        "output": "1. Overbevolking is een term die wordt gebruikt om de situatie in ve"
    },
    {
        "sample_idx": 48,
        "input_lang": "nl",
        "output": "Globalization is defined as “the process of creating world markets for goods and services by eliminating barriers"
    },
    {
        "sample_idx": 49,
        "input_lang": "nl",
        "output": "Remote working is becoming more common these days. discusses the advantages and disadvantages of remote working"
    }
]